llama_index_orpo_dpo_dataset_generator/__init__.py
llama_index_orpo_dpo_dataset_generator/labelled_orpo_dataset.py
llama_index_orpo_dpo_dataset_generator/orpo_data_example.py
llama_index_orpo_dpo_dataset_generator/orpo_dpo_dataset_generator.py
llama_index_orpo_dpo_dataset_generator-0.0.1.dist-info/METADATA
llama_index_orpo_dpo_dataset_generator-0.0.1.dist-info/WHEEL
llama_index_orpo_dpo_dataset_generator-0.0.1.dist-info/licenses/LICENSE
llama_index_orpo_dpo_dataset_generator-0.0.1.dist-info/RECORD
