Metadata-Version: 2.3
Name: llama_index_orpo_dpo_dataset_generator
Version: 0.0.1
Summary: A dataset generator for llama index to aid in generating ORPO & DPO datasets
Project-URL: Homepage, https://github.com/thesven/llama-index-orpo-dataset-generator
Project-URL: Issues, https://github.com/thesven/llama-index-orpo-dataset-generator/issues
Author-email: Example Author <michael@mikesvendsen.net>
License-File: LICENSE
Classifier: License :: OSI Approved :: MIT License
Classifier: Operating System :: OS Independent
Classifier: Programming Language :: Python :: 3
Requires-Python: >=3.10
